CHANGES.txt
LICENSE.txt
MANIFEST.in
README.txt
bootstrap.py
setup.py
eggs/ZConfig-4.2-py3.10.egg/EGG-INFO/LICENSE.txt
eggs/ZConfig-4.2-py3.10.egg/EGG-INFO/entry_points.txt
eggs/ZConfig-4.2-py3.10.egg/EGG-INFO/requires.txt
eggs/ZConfig-4.2-py3.10.egg/EGG-INFO/top_level.txt
eggs/ZConfig-4.2-py3.10.egg/ZConfig/schemaless.txt
eggs/ZConfig-4.2-py3.10.egg/ZConfig/tests/input/non-ascii.txt
eggs/ZConfig-4.2-py3.10.egg/ZConfig/tests/library/README.txt
eggs/ZConfig-4.2-py3.10.egg/ZConfig/tests/zipsource/README.txt
eggs/coverage-7.10.2-py3.10-win-amd64.egg/EGG-INFO/entry_points.txt
eggs/coverage-7.10.2-py3.10-win-amd64.egg/EGG-INFO/requires.txt
eggs/coverage-7.10.2-py3.10-win-amd64.egg/EGG-INFO/top_level.txt
eggs/coverage-7.10.2-py3.10-win-amd64.egg/EGG-INFO/licenses/LICENSE.txt
eggs/coverage-7.9.2-py3.10-win-amd64.egg/EGG-INFO/entry_points.txt
eggs/coverage-7.9.2-py3.10-win-amd64.egg/EGG-INFO/requires.txt
eggs/coverage-7.9.2-py3.10-win-amd64.egg/EGG-INFO/top_level.txt
eggs/coverage-7.9.2-py3.10-win-amd64.egg/EGG-INFO/licenses/LICENSE.txt
eggs/lovely.recipe-1.0.0-py3.10.egg/EGG-INFO/SOURCES.txt
eggs/lovely.recipe-1.0.0-py3.10.egg/EGG-INFO/dependency_links.txt
eggs/lovely.recipe-1.0.0-py3.10.egg/EGG-INFO/entry_points.txt
eggs/lovely.recipe-1.0.0-py3.10.egg/EGG-INFO/namespace_packages.txt
eggs/lovely.recipe-1.0.0-py3.10.egg/EGG-INFO/requires.txt
eggs/lovely.recipe-1.0.0-py3.10.egg/EGG-INFO/top_level.txt
eggs/lovely.recipe-1.0.0-py3.10.egg/lovely/recipe/egg/README.txt
eggs/lovely.recipe-1.0.0-py3.10.egg/lovely/recipe/fs/README.txt
eggs/lovely.recipe-1.0.0-py3.10.egg/lovely/recipe/fs/mkdir-root.txt
eggs/lovely.recipe-1.0.0-py3.10.egg/lovely/recipe/i18n/README.txt
eggs/lovely.recipe-1.0.0-py3.10.egg/lovely/recipe/importchecker/README.txt
eggs/p01.recipe.setup-0.8.19-py3.10.egg/EGG-INFO/SOURCES.txt
eggs/p01.recipe.setup-0.8.19-py3.10.egg/EGG-INFO/dependency_links.txt
eggs/p01.recipe.setup-0.8.19-py3.10.egg/EGG-INFO/entry_points.txt
eggs/p01.recipe.setup-0.8.19-py3.10.egg/EGG-INFO/namespace_packages.txt
eggs/p01.recipe.setup-0.8.19-py3.10.egg/EGG-INFO/requires.txt
eggs/p01.recipe.setup-0.8.19-py3.10.egg/EGG-INFO/top_level.txt
eggs/p01.recipe.setup-0.8.19-py3.10.egg/p01/recipe/setup/README.txt
eggs/p01.recipe.setup-0.8.19-py3.10.egg/p01/recipe/setup/checker.txt
eggs/p01.recipe.setup-0.8.19-py3.10.egg/p01/recipe/setup/cmd.txt
eggs/p01.recipe.setup-0.8.19-py3.10.egg/p01/recipe/setup/copy.txt
eggs/p01.recipe.setup-0.8.19-py3.10.egg/p01/recipe/setup/download.txt
eggs/p01.recipe.setup-0.8.19-py3.10.egg/p01/recipe/setup/fetch.txt
eggs/p01.recipe.setup-0.8.19-py3.10.egg/p01/recipe/setup/i18n.txt
eggs/p01.recipe.setup-0.8.19-py3.10.egg/p01/recipe/setup/importchecker.txt
eggs/p01.recipe.setup-0.8.19-py3.10.egg/p01/recipe/setup/index.txt
eggs/p01.recipe.setup-0.8.19-py3.10.egg/p01/recipe/setup/mkdir.txt
eggs/p01.recipe.setup-0.8.19-py3.10.egg/p01/recipe/setup/mkfile.txt
eggs/p01.recipe.setup-0.8.19-py3.10.egg/p01/recipe/setup/paste.txt
eggs/p01.recipe.setup-0.8.19-py3.10.egg/p01/recipe/setup/script.txt
eggs/p01.recipe.setup-0.8.19-py3.10.egg/p01/recipe/setup/scripts.txt
eggs/p01.recipe.setup-0.8.19-py3.10.egg/p01/recipe/setup/supervisor.txt
eggs/p01.recipe.setup-0.8.19-py3.10.egg/p01/recipe/setup/template.txt
eggs/p01.recipe.setup-0.8.19-py3.10.egg/p01/recipe/setup/winservice.txt
eggs/six-1.17.0-py3.10.egg/EGG-INFO/top_level.txt
eggs/testrunner-0.8.4-py3.10.egg/EGG-INFO/SOURCES.txt
eggs/testrunner-0.8.4-py3.10.egg/EGG-INFO/dependency_links.txt
eggs/testrunner-0.8.4-py3.10.egg/EGG-INFO/top_level.txt
eggs/z3c.coverage-2.1.0-py3.10.egg/EGG-INFO/SOURCES.txt
eggs/z3c.coverage-2.1.0-py3.10.egg/EGG-INFO/dependency_links.txt
eggs/z3c.coverage-2.1.0-py3.10.egg/EGG-INFO/entry_points.txt
eggs/z3c.coverage-2.1.0-py3.10.egg/EGG-INFO/namespace_packages.txt
eggs/z3c.coverage-2.1.0-py3.10.egg/EGG-INFO/requires.txt
eggs/z3c.coverage-2.1.0-py3.10.egg/EGG-INFO/top_level.txt
eggs/z3c.coverage-2.1.0-py3.10.egg/z3c/coverage/README.txt
eggs/z3c.coverage-2.1.0-py3.10.egg/z3c/coverage/coveragediff.txt
eggs/zc.recipe.egg-2.0.7-py3.10.egg/EGG-INFO/SOURCES.txt
eggs/zc.recipe.egg-2.0.7-py3.10.egg/EGG-INFO/dependency_links.txt
eggs/zc.recipe.egg-2.0.7-py3.10.egg/EGG-INFO/entry_points.txt
eggs/zc.recipe.egg-2.0.7-py3.10.egg/EGG-INFO/namespace_packages.txt
eggs/zc.recipe.egg-2.0.7-py3.10.egg/EGG-INFO/requires.txt
eggs/zc.recipe.egg-2.0.7-py3.10.egg/EGG-INFO/top_level.txt
eggs/zc.recipe.testrunner-3.2-py3.10.egg/EGG-INFO/LICENSE.txt
eggs/zc.recipe.testrunner-3.2-py3.10.egg/EGG-INFO/entry_points.txt
eggs/zc.recipe.testrunner-3.2-py3.10.egg/EGG-INFO/namespace_packages.txt
eggs/zc.recipe.testrunner-3.2-py3.10.egg/EGG-INFO/requires.txt
eggs/zc.recipe.testrunner-3.2-py3.10.egg/EGG-INFO/top_level.txt
eggs/zope.component-6.0-py3.10.egg/EGG-INFO/LICENSE.txt
eggs/zope.component-6.0-py3.10.egg/EGG-INFO/namespace_packages.txt
eggs/zope.component-6.0-py3.10.egg/EGG-INFO/requires.txt
eggs/zope.component-6.0-py3.10.egg/EGG-INFO/top_level.txt
eggs/zope.event-5.0-py3.10.egg/EGG-INFO/LICENSE.txt
eggs/zope.event-5.0-py3.10.egg/EGG-INFO/namespace_packages.txt
eggs/zope.event-5.0-py3.10.egg/EGG-INFO/requires.txt
eggs/zope.event-5.0-py3.10.egg/EGG-INFO/top_level.txt
eggs/zope.exceptions-5.2-py3.10.egg/EGG-INFO/LICENSE.txt
eggs/zope.exceptions-5.2-py3.10.egg/EGG-INFO/namespace_packages.txt
eggs/zope.exceptions-5.2-py3.10.egg/EGG-INFO/requires.txt
eggs/zope.exceptions-5.2-py3.10.egg/EGG-INFO/top_level.txt
eggs/zope.hookable-7.0-py3.10-win-amd64.egg/EGG-INFO/LICENSE.txt
eggs/zope.hookable-7.0-py3.10-win-amd64.egg/EGG-INFO/namespace_packages.txt
eggs/zope.hookable-7.0-py3.10-win-amd64.egg/EGG-INFO/requires.txt
eggs/zope.hookable-7.0-py3.10-win-amd64.egg/EGG-INFO/top_level.txt
eggs/zope.interface-7.2-py3.10-win-amd64.egg/EGG-INFO/LICENSE.txt
eggs/zope.interface-7.2-py3.10-win-amd64.egg/EGG-INFO/namespace_packages.txt
eggs/zope.interface-7.2-py3.10-win-amd64.egg/EGG-INFO/requires.txt
eggs/zope.interface-7.2-py3.10-win-amd64.egg/EGG-INFO/top_level.txt
